ttpalette/__init__.py
ttpalette/ttpalette.py
ttpalette-0.1.1.dist-info/LICENSE
ttpalette-0.1.1.dist-info/METADATA
ttpalette-0.1.1.dist-info/WHEEL
ttpalette-0.1.1.dist-info/top_level.txt
ttpalette-0.1.1.dist-info/RECORD
