Metadata-Version: 2.1
Name: ttpalette
Version: 0.1.1
Summary: A library for coloring texts in the terminal
Author-email: kinite-gp <kinitegp@gmail.com>
Classifier: Programming Language :: Python :: 3
Classifier: License :: OSI Approved :: MIT License
Classifier: Operating System :: OS Independent
Requires-Python: >=3.8
License-File: LICENSE
